intctl/__init__.py
intctl/cli.py
intctl/complete.py
intctl/config.py
intctl/login.py
intctl/setup.py
intctl/status.py
intctl/sync.py
intctl/gcp_resources/bucket.py
intctl/gcp_resources/create_subdomain.py
intctl/gcp_resources/deploy.py
intctl/gcp_resources/enable_required_apis.py
intctl/gcp_resources/finalise_database.py
intctl/gcp_resources/gateway.py
intctl/gcp_resources/gitea.py
intctl/gcp_resources/kubernetes.py
intctl/gcp_resources/postgres.py
intctl/gcp_resources/registry.py
intctl/gcp_resources/service_account.py
intctl/gcp_resources/utils.py
intctl/gcp_resources/vpc.py
intctl/k8s/README.md
intctl/k8s/openapi-spec.yaml
intctl/k8s/gateway-manager/deployment.yaml
intctl/k8s/gateway-manager/hpa.yaml
intctl/k8s/gateway-manager/namespace.yaml
intctl/k8s/gateway-manager/secret.yaml
intctl/k8s/gateway-manager/service.yaml
intctl/k8s/gitea/deployment.yaml
intctl/k8s/gitea/gitea-config-template-cm.yaml
intctl/k8s/gitea/gitea-init-script-cm.yaml
intctl/k8s/gitea/hpa.yaml
intctl/k8s/gitea/namespace.yaml
intctl/k8s/gitea/secret.yaml
intctl/k8s/gitea/service.yaml
intctl/k8s/gitea/volume.yaml
intctl/k8s/gitea-manager/deployment.yaml
intctl/k8s/gitea-manager/hpa.yaml
intctl/k8s/gitea-manager/namespace.yaml
intctl/k8s/gitea-manager/secret.yaml
intctl/k8s/gitea-manager/service.yaml
intctl/k8s/mlflow/deployment.yaml
intctl/k8s/mlflow/hpa.yaml
intctl/k8s/mlflow/namespace.yaml
intctl/k8s/mlflow/pvc.yaml
intctl/k8s/mlflow/secret.yaml
intctl/k8s/mlflow/service.yaml
intctl/k8s/mlflow-manager/deployment.yaml
intctl/k8s/mlflow-manager/hpa.yaml
intctl/k8s/mlflow-manager/namespace.yaml
intctl/k8s/mlflow-manager/secret.yaml
intctl/k8s/mlflow-manager/service.yaml
intctl/k8s/project-manager/deployment.yaml
intctl/k8s/project-manager/hpa.yaml
intctl/k8s/project-manager/namespace.yaml
intctl/k8s/project-manager/secret.yaml
intctl/k8s/project-manager/service.yaml
intctl/k8s/resource-manager/deployment.yaml
intctl/k8s/resource-manager/hpa.yaml
intctl/k8s/resource-manager/namespace.yaml
intctl-1.0.21.dist-info/METADATA
intctl-1.0.21.dist-info/WHEEL
intctl-1.0.21.dist-info/entry_points.txt
intctl-1.0.21.dist-info/top_level.txt
intctl-1.0.21.dist-info/RECORD
